tadgrad/__init__.py
tadgrad/layers.py
tadgrad/network.py
tadgrad/optim.py
tadgrad/py.typed
tadgrad/typedefs.py
tadgrad/utils.py
tadgrad/activations/__init__.py
tadgrad/activations/aff.py
tadgrad/activations/lin.py
tadgrad/activations/relu.py
tadgrad/activations/sigmoid.py
tadgrad/losses/__init__.py
tadgrad/losses/mae.py
tadgrad/losses/mse.py
tadgrad-0.1.1.dist-info/LICENSE
tadgrad-0.1.1.dist-info/METADATA
tadgrad-0.1.1.dist-info/WHEEL
tadgrad-0.1.1.dist-info/top_level.txt
tadgrad-0.1.1.dist-info/RECORD
