Metadata-Version: 2.1
Name: tadgrad
Version: 0.1.1
Summary: Machine Learning from scratch
Home-page: https://github.com/cospectrum/tadgrad.git
Author: Alexey Severin
License: MIT
Keywords: python
Platform: UNKNOWN
License-File: LICENSE
Requires-Dist: pylinal (==0.1.5)
